{
  "type": "FeatureCollection",
  "generator": "overpass-ide",
  "copyright": "The data included in this document is from www.openstreetmap.org. The data is made available under ODbL.",
  "timestamp": "2020-08-27T10:45:03Z",
  "features": [
    {
      "type": "Feature",
      "properties": {
        "@id": "6",
        "name": "Cua Chinh Nha Dieu hanh A1"
      },
      "geometry": {
        "type": "Polygon",
        "coordinates": [
          [

            [ 106.80280132306, 10.8702129754769, 30 ],
            [ 106.802802140062, 10.8702260659820, 30 ],
            [ 106.802808365566, 10.8702407017395, 30 ]





          ]
        ]
      },
      "id": "6"
    },
    {
      "type": "Feature",
      "properties": {
        "@id": "6",
        "name": "Cua Chinh Nha Dieu hanh A1"
      },
      "geometry": {
        "type": "Polygon",
        "coordinates": [
          [

            [ 106.802812937761, 10.8701628848900, 30 ],
            [ 106.802806470121, 10.8701747973363, 30 ],
            [ 106.802800002481, 10.8701894097826, 30 ]





          ]
        ]
      },
      "id": "6"
    }
  ]
}
  